tp_package/__init__.py
tp_package/utils.py
tp_package-0.3.dist-info/METADATA
tp_package-0.3.dist-info/WHEEL
tp_package-0.3.dist-info/top_level.txt
tp_package-0.3.dist-info/RECORD
