Metadata-Version: 2.1
Name: tp_package
Version: 0.3
Summary: A modern Python project using pyproject.toml and setuptools
Author-email: Your Name <you@example.com>
Keywords: example,setuptools,pyproject
Classifier: Programming Language :: Python :: 3
Classifier: License :: OSI Approved :: MIT License
Classifier: Operating System :: OS Independent
Requires-Dist: requests>=2.30.0
